[
  {
    "Компанія": "Fenris GmbH",
    "Email": "hr@fenris-group.com",
    "Ім’я": "",
    "Посада": "Web Developer",
    "Лінк": "https://www.make-it-in-germany.com/en/working-in-germany/job-listings/job/job-10000-1198344265-S",
    "Статус": "",
    "Дата відправки": "",
    "Відповідь": "",
    "Коментар": "",
    "Мова": "en",
    "Стать": ""
  },
  {
    "Компанія": "NextTech Solutions",
    "Email": "jobs@nexttech.dev",
    "Ім’я": "Anna",
    "Посада": "Frontend Developer (React)",
    "Лінк": "https://nexttech.dev/careers/frontend-react",
    "Статус": "",
    "Дата відправки": "",
    "Відповідь": "",
    "Коментар": "",
    "Мова": "en",
    "Стать": "ж"
  }
]